{
    "fdInfo": {
        "eName": "Probation", 
        "cName": "缓刑", 
        "des": "缓刑是指对于被判处拘役、3年以下有期徒刑的犯罪人，根据其犯罪情节和悔罪表现，如果暂缓执行刑罚确实不致再危害社会，就规定一定的考验期，暂缓刑罚的执行；在考验期内，如果遵守一定条件，原判刑罚就不再执行的一项制度。"
    }, 
    "lexElmt": [
        {
            "word": "当选", 
            "POS": "v"
        }, 
        {
            "word": "缓刑", 
            "POS": "v"
        }
    ], 
    "element": [
        {
            "abbrName": null, 
            "eName": null, 
            "cName": "犯罪人", 
            "isCore": true, 
            "def": "因为犯罪行为被判处刑罚，且因其犯罪情节和悔罪表现，被法院宣告缓刑的人。"
        }, 
        {
            "abbrName": null, 
            "eName": null, 
            "cName": "法院", 
            "isCore": true, 
            "def": "对犯罪人定罪判刑，并对其宣告缓刑的法院。"
        }, 
        {
            "abbrName": null, 
            "eName": null, 
            "cName": "罪行", 
            "isCore": true, 
            "def": "犯罪人所做出的严重危害社会的行为。"
        }, 
        {
            "abbrName": null, 
            "eName": null, 
            "cName": "刑罚", 
            "isCore": true, 
            "def": "法院对犯罪人的罪行依法做出的惩罚"
        }, 
        {
            "abbrName": null, 
            "eName": null, 
            "cName": "考验期", 
            "isCore": true, 
            "def": "法院根据犯罪人确定的考验时间，在此期间，如犯罪人遵守一定条件，则不再执行原判刑罚。"
        }, 
        {
            "abbrName": null, 
            "eName": null, 
            "cName": "条件", 
            "isCore": false, 
            "def": "对犯罪人适用缓刑所需要的条件"
        }, 
        {
            "abbrName": null, 
            "eName": null, 
            "cName": "时间", 
            "isCore": false, 
            "def": "法院做出判决，宣告缓刑的时间"
        }
    ]
}